files_and_folders/__init__.py
files_and_folders/files.py
files_and_folders/folders.py
files_and_folders/images.py
files_and_folders/pdfs.py
ibott_files-1.0.8.dist-info/LICENSE
ibott_files-1.0.8.dist-info/METADATA
ibott_files-1.0.8.dist-info/WHEEL
ibott_files-1.0.8.dist-info/top_level.txt
ibott_files-1.0.8.dist-info/RECORD
