Metadata-Version: 2.1
Name: ibott-files
Version: 1.0.8
Summary: This packages crates a simple way to work with, files, folders, images and pdfs.
Home-page: https://github.com/ecrespo66/files_and_folders
Author: OnameDohe
Author-email: OnameDohe <enrique.crespo.debenito@gmail.com>
License: Apache License
Project-URL: Homepage, https://github.com/ecrespo66/files_and_folders
Project-URL: Bug Tracker, https://github.com/ecrespo66/files_and_folders/issues
Classifier: Programming Language :: Python :: 3
Classifier: License :: OSI Approved :: MIT License
Classifier: Operating System :: OS Independent
Requires-Python: >=3.6
License-File: LICENSE
Requires-Dist: hatchling
Requires-Dist: Pillow
Requires-Dist: PyPDF2
Requires-Dist: requests
Requires-Dist: PyMuPDF
